stocker/__init__.py
stocker/error.py
stocker/get_data.py
stocker/lstm.py
stocker/predict.py
stocker-0.1.11.dist-info/LICENSE
stocker-0.1.11.dist-info/METADATA
stocker-0.1.11.dist-info/WHEEL
stocker-0.1.11.dist-info/top_level.txt
stocker-0.1.11.dist-info/RECORD
