Metadata-Version: 2.1
Name: stocker
Version: 0.1.11
Summary: Stock Price Prediction
Home-page: https://github.com/jcamiloangarita/stocker
Author: jcamiloangarita
Author-email: camiloang94@gmail.com
License: UNKNOWN
Keywords: stock price prediction
Platform: UNKNOWN
Classifier: Programming Language :: Python :: 3
Classifier: Natural Language :: English
Classifier: Topic :: Utilities
Requires-Dist: numpy
Requires-Dist: yfinance
Requires-Dist: pytrends
Requires-Dist: pandas
Requires-Dist: requests
Requires-Dist: scikit-learn
Requires-Dist: tensorflow
Requires-Dist: matplotlib
